cabinet/__init__.py
cabinet/__main__.py
cabinet/cabinet.py
cabinet/constants.py
cabinet/helpers.py
cabinet/mail.py
cabinet-2024.7.20.1.dist-info/LICENSE
cabinet-2024.7.20.1.dist-info/METADATA
cabinet-2024.7.20.1.dist-info/WHEEL
cabinet-2024.7.20.1.dist-info/entry_points.txt
cabinet-2024.7.20.1.dist-info/top_level.txt
cabinet-2024.7.20.1.dist-info/RECORD
