Metadata-Version: 2.1
Name: cabinet
Version: 2024.7.20.1
Summary: Easily manage data storage and logging across repos
Home-page: https://github.com/tylerjwoodfin/cabinet
Author: Tyler Woodfin
Author-email: feedback@tyler.cloud
License: : OSI Approved :: MIT License
Requires-Python: >=3.6
License-File: LICENSE
